google/shopping/merchant_ordertracking/__init__.py
google/shopping/merchant_ordertracking/gapic_version.py
google/shopping/merchant_ordertracking/py.typed
google/shopping/merchant_ordertracking_v1/__init__.py
google/shopping/merchant_ordertracking_v1/gapic_metadata.json
google/shopping/merchant_ordertracking_v1/gapic_version.py
google/shopping/merchant_ordertracking_v1/py.typed
google/shopping/merchant_ordertracking_v1/services/__init__.py
google/shopping/merchant_ordertracking_v1/services/order_tracking_signals_service/__init__.py
google/shopping/merchant_ordertracking_v1/services/order_tracking_signals_service/async_client.py
google/shopping/merchant_ordertracking_v1/services/order_tracking_signals_service/client.py
google/shopping/merchant_ordertracking_v1/services/order_tracking_signals_service/transports/__init__.py
google/shopping/merchant_ordertracking_v1/services/order_tracking_signals_service/transports/base.py
google/shopping/merchant_ordertracking_v1/services/order_tracking_signals_service/transports/grpc.py
google/shopping/merchant_ordertracking_v1/services/order_tracking_signals_service/transports/grpc_asyncio.py
google/shopping/merchant_ordertracking_v1/services/order_tracking_signals_service/transports/rest.py
google/shopping/merchant_ordertracking_v1/services/order_tracking_signals_service/transports/rest_base.py
google/shopping/merchant_ordertracking_v1/types/__init__.py
google/shopping/merchant_ordertracking_v1/types/order_tracking_signals.py
google/shopping/merchant_ordertracking_v1beta/__init__.py
google/shopping/merchant_ordertracking_v1beta/gapic_metadata.json
google/shopping/merchant_ordertracking_v1beta/gapic_version.py
google/shopping/merchant_ordertracking_v1beta/py.typed
google/shopping/merchant_ordertracking_v1beta/services/__init__.py
google/shopping/merchant_ordertracking_v1beta/services/order_tracking_signals_service/__init__.py
google/shopping/merchant_ordertracking_v1beta/services/order_tracking_signals_service/async_client.py
google_shopping_merchant_ordertracking-1.2.0.dist-info/licenses/LICENSE
google_shopping_merchant_ordertracking-1.2.0.dist-info/METADATA
google_shopping_merchant_ordertracking-1.2.0.dist-info/WHEEL
google_shopping_merchant_ordertracking-1.2.0.dist-info/top_level.txt
google_shopping_merchant_ordertracking-1.2.0.dist-info/RECORD
